expansehost/__init__.py
expansehost/exceptions.py
expansehost/server.py
expansehost/util.py
expansehost-1.0.3.dist-info/LICENSE
expansehost-1.0.3.dist-info/METADATA
expansehost-1.0.3.dist-info/WHEEL
expansehost-1.0.3.dist-info/top_level.txt
expansehost-1.0.3.dist-info/RECORD
