Metadata-Version: 2.1
Name: expansehost
Version: 1.0.3
Summary: A Python API Wrapper for the expansehost API
Home-page: https://github.com/cyklon73/expansehost
Author: Cyklon73
Author-email: cyklon698@gmail.com
License: MIT
Classifier: Programming Language :: Python :: 3.10
Classifier: Programming Language :: Python :: 3.11
License-File: LICENSE
